<?xml version="1.0" encoding="UTF-8"?>
<Missions>
 <mission name="Cargo Custom">
  <lua>cargo_custom</lua>
  <avail>
   <priority>8</priority>
   <!-- forty missions at 100% chance. Will be lowered within mission script itself -->
   <chance>4000</chance>
   <location>Computer</location>
   <!-- should be basically everybody with a mission computer -->
   <faction>Empire of Terra</faction>
   <faction>Independent Worlds</faction>
   <faction>Roidhunate of Ardarshir</faction>
   <faction>Oligarchy of Betelgeuse</faction>
   <faction>Kingdom of Ixum</faction>
   <faction>Holy Flame of Ixum</faction>
  </avail>
 </mission>
 <mission name="The Great Survey Intro">
  <lua>greatsurvey/great_survey_intro</lua>
  <avail>
   <priority>5</priority>
   <chance>100</chance>
   <location>Bar</location>
   <faction>Empire of Terra</faction>
  </avail>
  <flags>
   <unique />
  </flags>
 </mission>
 <mission name="The Great Survey Rec">
  <lua>greatsurvey/great_survey_rec</lua>
  <avail>
    <priority>5</priority>
    <chance>100</chance>
    <location>Space</location>
    <done>The Great Survey Intro</done>
  </avail>
  <flags>
   <unique />
  </flags>
 </mission>
 <mission name="Economy Student">
  <lua>intro/ardarshir</lua>
  <avail>
   <priority>5</priority>
   <chance>100</chance>
   <location>Bar</location>
   <faction>Empire of Terra</faction>
  </avail>
  <flags>
   <unique />
  </flags>
 </mission>
 <mission name="Betelgeusan Trade">
  <lua>intro/betelgeuse</lua>
  <avail>
   <priority>5</priority>
   <chance>100</chance>
   <location>Bar</location>
   <faction>Empire of Terra</faction>
  </avail>
  <flags>
   <unique />
  </flags>
 </mission>
 <mission name="Empire Pirate Elimination">
  <lua>empiremilitary/pirate_bounty_bar</lua>
  <flags>
   <unique />
  </flags>
  <avail>
   <priority>5</priority>
   <chance>100</chance>
   <location>Bar</location>
   <faction>Empire of Terra</faction>
  </avail>
 </mission>
<mission name="Empire Pirate Elimination Recuring">
  <lua>empiremilitary/pirate_bounty_rec</lua>
  <avail>
   <priority>5</priority>
   <chance>100</chance>
   <done>Empire Pirate Elimination</done>
   <location>Computer</location>
   <faction>Empire of Terra</faction>
  </avail>
 </mission>
 <mission name="Empire Barbarian Scouting">
  <lua>empiremilitary/barbarian_recon_bar</lua>
  <flags>
   <unique />
  </flags>
  <avail>
   <priority>15</priority>
   <chance>100</chance>
   <location>Bar</location>
   <faction>Empire of Terra</faction>
  </avail>
 </mission>
 <mission name="Empire Barbarian Scouting Rec">
  <lua>empiremilitary/barbarian_recon_rec</lua>
  <avail>
   <priority>5</priority>
   <chance>100</chance>
   <done>Empire Barbarian Scouting</done>
   <location>Computer</location>
   <faction>Empire of Terra</faction>
  </avail>
 </mission>
   <mission name="Empire Barbarian Elimination">
  <lua>empiremilitary/barbarian_leader_bar</lua>
  <flags>
   <unique />
  </flags>
  <avail>
   <priority>5</priority>
   <chance>100</chance>
   <done>Empire Barbarian Scouting</done>
   <location>Bar</location>
   <faction>Empire of Terra</faction>
  </avail>
 </mission>
  <mission name="Empire Barbarian Elimination Rec">
  <lua>empiremilitary/barbarian_leader_rec</lua>
  <avail>
   <priority>5</priority>
   <chance>100</chance>
   <done>Empire Barbarian Elimination</done>
   <location>Computer</location>
   <faction>Empire of Terra</faction>
  </avail>
 </mission>
 <mission name="Empire Ardar Scouting">
  <lua>empiremilitary/ardarshir_recon_bar</lua>
  <flags>
   <unique />
  </flags>
  <avail>
   <priority>15</priority>
   <chance>100</chance>
   <done>Empire Barbarian Scouting</done>
   <location>Bar</location>
   <faction>Empire of Terra</faction>
  </avail>
 </mission>
 <mission name="Empire Ardar Scouting Rec">
  <lua>empiremilitary/ardarshir_recon_rec</lua>
  <avail>
   <priority>5</priority>
   <chance>100</chance>
   <done>Empire Ardar Scouting</done>
   <location>Computer</location>
   <faction>Empire of Terra</faction>
  </avail>
 </mission>

 <mission name="Intro 1">
  <lua>introquest/intro_1</lua>
  <flags>
   <unique />
  </flags>
  <avail>
   <priority>5</priority>
   <chance>20</chance>
   <location>Space</location>
  </avail>
 </mission>
  <mission name="Intro 2">
  <lua>introquest/intro_2</lua>
  <flags>
   <unique />
  </flags>
  <avail>
   <priority>5</priority>
   <chance>100</chance>
   <done>Intro 1</done>
   <location>Land</location>
  </avail>
 </mission>
   <mission name="Intro 3">
  <lua>introquest/intro_3</lua>
  <flags>
   <unique />
  </flags>
  <avail>
   <priority>5</priority>
   <chance>100</chance>
   <done>Intro 2</done>
   <location>Land</location>
  </avail>
 </mission>

 <mission name="Harkan 1">
  <lua>mainquest1/harkan_1</lua>
  <flags>
   <unique />
  </flags>
  <avail>
   <priority>5</priority>
   <chance>10</chance>
   <done>Intro 3</done>
   <location>Space</location>
  </avail>
 </mission>
 <mission name="Harkan 2">
  <lua>mainquest1/harkan_2</lua>
  <flags>
   <unique />
  </flags>
  <avail>
   <priority>5</priority>
   <chance>100</chance>
   <done>Harkan 1</done>
   <location>Land</location>
  </avail>
 </mission>
 <mission name="Harkan 2 Delivery Rec">
  <lua>mainquest1/harkan_2_delivery_rec</lua>
  <avail>
   <priority>150</priority>
   <chance>50</chance>
   <done>Harkan 2</done>
   <cond>not var.peek("harkan_roidhunate_choice")</cond>
   <location>Computer</location>
   <faction>Empire of Terra</faction>
  </avail>
 </mission>
 <mission name="Harkan 2 Kill Rec">
  <lua>mainquest1/harkan_2_kill_rec</lua>
  <avail>
   <priority>150</priority>
   <chance>50</chance>
   <done>Harkan 2</done>
   <cond>not var.peek("harkan_roidhunate_choice")</cond>
   <location>Computer</location>
   <faction>Empire of Terra</faction>
  </avail>
 </mission>
 <mission name="Harkan 3">
  <lua>mainquest1/harkan_3</lua>
  <flags>
   <unique />
  </flags>
  <avail>
   <priority>5</priority>
   <chance>100</chance>
   <done>Harkan 2</done>
   <cond>var.peek("harkan_3_start_time") ~= nil and time.get() &gt; time.fromnumber( var.peek("harkan_3_start_time") )</cond>
   <location>Space</location>
  </avail>
 </mission>
 <mission name="Harkan 4">
  <lua>mainquest1/harkan_4</lua>
  <flags>
   <unique />
  </flags>
  <avail>
   <priority>5</priority>
   <chance>100</chance>
   <done>Harkan 3</done>
   <location>Land</location>
  </avail>
 </mission>
 <mission name="Harkan 5">
  <lua>mainquest1/harkan_5</lua>
  <flags>
   <unique />
  </flags>
  <avail>
   <priority>5</priority>
   <chance>100</chance>
   <done>Harkan 4</done>
   <cond>var.peek("harkan_5_start_time") ~= nil and time.get() &gt; time.fromnumber( var.peek("harkan_5_start_time") )</cond>
   <location>Space</location>
  </avail>
 </mission>
 <mission name="Harkan Empire 6">
  <lua>mainquest1/harkan_empire_6</lua>
  <flags>
   <unique />
  </flags>
  <avail>
   <priority>5</priority>
   <chance>100</chance>
   <done>Harkan 5</done>
   <cond>var.peek("harkan_empire_choice")==true</cond>
   <location>Land</location>
  </avail>
 </mission>
 <mission name="Harkan Empire 7">
  <lua>mainquest1/harkan_empire_7</lua>
  <flags>
   <unique />
  </flags>
  <avail>
   <priority>5</priority>
   <chance>100</chance>
   <done>Harkan Empire 6</done>
   <location>Land</location>
  </avail>
 </mission>
 <mission name="Harkan Empire 8">
  <lua>mainquest1/harkan_empire_8</lua>
  <flags>
   <unique />
  </flags>
  <avail>
   <priority>5</priority>
   <chance>100</chance>
   <done>Harkan Empire 7</done>
   <location>Land</location>
  </avail>
 </mission>
 <mission name="Harkan Roidhunate 6">
  <lua>mainquest1/harkan_roidhunate_6</lua>
  <flags>
   <unique />
  </flags>
  <avail>
   <priority>5</priority>
   <chance>100</chance>
   <done>Harkan 5</done>
   <cond>var.peek("harkan_roidhunate_choice")==true and var.peek("harkan_roidhunate_6_start_time") ~= nil and time.get() &gt; time.fromnumber( var.peek("harkan_roidhunate_6_start_time") )</cond>
   <location>Space</location>
  </avail>
 </mission>
<mission name="Harkan Roidhunate 7">
  <lua>mainquest1/harkan_roidhunate_7</lua>
  <flags>
   <unique />
  </flags>
  <avail>
   <priority>5</priority>
   <chance>100</chance>
   <done>Harkan Roidhunate 6</done>
   <cond>var.peek("harkan_roidhunate_7_start_time") ~= nil and time.get() &gt; time.fromnumber( var.peek("harkan_roidhunate_7_start_time") )</cond>
   <location>Space</location>
  </avail>
 </mission>
 <mission name="Tutorial Mission">
  <lua>tutorial/tutmis</lua>
  <flags>
   <unique />
  </flags>
  <avail>
   <location>None</location>
  </avail>
 </mission>
</Missions>