<?xml version='1.0' encoding='UTF-8'?>
<ship name='Pirate Vendetta'>
 <base_type>Vendetta</base_type>
 <short_name>Vendetta</short_name>
 <GFX sx="8" sy="8">vendetta_pirate</GFX>
 <GUI>slim</GUI>
 <sound>engine</sound>
 <class>Destroyer</class>
 <fabricator>Pirate Shipyards</fabricator>
 <description>With a greater range, a more powerful engine and boosted weapon capacities, the pirate variants of the famous vendetta design make excellent piracy vessels.</description>
 <price>2200000</price>
 <logo>pirates</logo>
 <rating_military>3</rating_military>
 <rating_utility>1</rating_utility>
 <rating_agility>6</rating_agility>
 <movement>
  <thrust>200</thrust>
  <turn>100</turn>
  <speed>190</speed>
  <engine_limit>600</engine_limit>
 </movement>
 <health>
  <absorb>15</absorb>
  <shield>250</shield>
  <armour>400</armour>
  <energy>500</energy>
  <shield_regen>4</shield_regen>
  <armour_regen>0</armour_regen>
  <energy_regen>30</energy_regen>
 </health>
 <characteristics>
  <cpu>50</cpu>
  <crew>15</crew>
  <mass>380</mass>
  <fuel>600</fuel>
  <fuel_consumption>150</fuel_consumption>
  <cargo>40</cargo>
 </characteristics>
<stats>
  
</stats>
<slots>
<weapon size="medium" x="16" y="-9" h="0" />
<weapon size="medium" x="16" y="9" h="0" />
<weapon size="medium" x="13" y="-13" h="0" />
<weapon size="medium" x="13" y="13" h="0" />
<weapon size="small" x="19" y="0" h="-2" />
<weapon size="small" x="3" y="0" h="2" />
<utility size="medium"/>
<utility size="small"/>
<structure size="medium"/>
<structure size="medium"/>
<structure size="small"/>
<structure size="small"/>
</slots>

</ship>